hyperwallet/__init__.py
hyperwallet/api.py
hyperwallet/config.py
hyperwallet/exceptions.py
hyperwallet/models.py
hyperwallet/tests/__init__.py
hyperwallet/tests/test_api.py
hyperwallet/tests/test_client.py
hyperwallet/tests/test_encryption.py
hyperwallet/tests/test_models.py
hyperwallet/utils/__init__.py
hyperwallet/utils/apiclient.py
hyperwallet/utils/encryption.py
hyperwallet_sdk-1.7.2.dist-info/LICENSE
hyperwallet_sdk-1.7.2.dist-info/METADATA
hyperwallet_sdk-1.7.2.dist-info/WHEEL
hyperwallet_sdk-1.7.2.dist-info/top_level.txt
hyperwallet_sdk-1.7.2.dist-info/RECORD
