Metadata-Version: 2.1
Name: hyperwallet-sdk
Version: 1.7.2
Summary: A Python wrapper around the Hyperwallet API
Home-page: https://github.com/hyperwallet/python-sdk
Author: The Hyperwallet Developers
Author-email: devsupport@hyperwallet.com
Maintainer: The Hyperwallet Developers
Maintainer-email: devsupport@hyperwallet.com
License: MIT
Keywords: hyperwallet api
Classifier: Development Status :: 4 - Beta
Classifier: Framework :: Sphinx
Classifier: Intended Audience :: Developers
Classifier: Natural Language :: English
Classifier: Programming Language :: Python
Classifier: Programming Language :: Python :: 3
Classifier: Programming Language :: Python :: 3.7
Classifier: Programming Language :: Python :: 3.8
Classifier: Programming Language :: Python :: 3.9
Classifier: Programming Language :: Python :: 3.10
Classifier: Programming Language :: Python :: 3.11
Classifier: Topic :: Internet
Classifier: Topic :: Software Development :: Libraries :: Python Modules
License-File: LICENSE
Requires-Dist: requests
Requires-Dist: requests-toolbelt
Requires-Dist: jwcrypto
Requires-Dist: python-jose
